{
    "boxShadow": "none",
    "iconSVG": "/static/media/icon.bd99caba5853ad71e4b3d8daffacb3a2.svg",
    "labelText": "Course",
    "topRow": 6,
    "labelWidth": 5,
    "type": "SELECT_WIDGET",
    "serverSideFiltering": false,
    "topRowBeforeCollapse": 0,
    "defaultOptionValue": "{{ ((options, serverSideFiltering) => ( utils.moduleContent.moduleContent.course_id))(sel_updateCourse.options, sel_updateCourse.serverSideFiltering) }}",
    "animateLoading": true,
    "leftColumn": 18,
    "dynamicBindingPathList": [
        {"key": "accentColor"},
        {"key": "borderRadius"},
        {"key": "options"},
        {"key": "isDisabled"},
        {"key": "defaultOptionValue"}
    ],
    "options": "{{fetchCourseBySubject.data.map(c => {\n\treturn {\n\t\tlabel: c.course_name,\n\t\tvalue: c.course_id\n\t}\n})}}",
    "labelStyle": "BOLD",
    "placeholderText": "Select option",
    "isDisabled": "{{!sel_updateSubject.selectedOptionValue}}",
    "isRequired": true,
    "dynamicHeight": "FIXED",
    "accentColor": "{{appsmith.theme.colors.primaryColor}}",
    "bottomRowBeforeCollapse": 7,
    "isVisible": true,
    "version": 1,
    "isLoading": false,
    "borderRadius": "{{appsmith.theme.borderRadius.appBorderRadius}}",
    "originalBottomRow": 7,
    "mobileBottomRow": 9,
    "widgetName": "sel_updateCourse",
    "isFilterable": true,
    "dynamicPropertyPathList": [{"key": "isDisabled"}],
    "displayName": "Select",
    "searchTags": ["dropdown"],
    "bottomRow": 13,
    "parentRowSpace": 10,
    "hideCard": false,
    "mobileRightColumn": 39,
    "parentColumnSpace": 18.203125,
    "dynamicTriggerPathList": [],
    "labelPosition": "Top",
    "key": "ru5iwpo3rm",
    "labelTextSize": "0.875rem",
    "isDeprecated": false,
    "rightColumn": 34,
    "widgetId": "3s4smd3nz4",
    "minWidth": 450,
    "parentId": "0v97vwoqbv",
    "labelAlignment": "left",
    "renderMode": "CANVAS",
    "mobileTopRow": 2,
    "responsiveBehavior": "fill",
    "originalTopRow": 0,
    "mobileLeftColumn": 19,
    "maxDynamicHeight": 9000,
    "minDynamicHeight": 4
}