{
    "boxShadow": "none",
    "iconSVG": "/static/media/icon.9f505595da61a34f563dba82adeb06ec.svg",
    "topRow": 18,
    "labelWidth": 5,
    "type": "INPUT_WIDGET_V2",
    "animateLoading": true,
    "resetOnSubmit": true,
    "leftColumn": 1,
    "dynamicBindingPathList": [
        {"key": "accentColor"},
        {"key": "borderRadius"},
        {"key": "defaultText"}
    ],
    "labelStyle": "BOLD",
    "inputType": "MULTI_LINE_TEXT",
    "isDisabled": false,
    "isRequired": false,
    "dynamicHeight": "FIXED",
    "accentColor": "{{appsmith.theme.colors.primaryColor}}",
    "showStepArrows": false,
    "isVisible": true,
    "version": 2,
    "isLoading": false,
    "borderRadius": "{{appsmith.theme.borderRadius.appBorderRadius}}",
    "mobileBottomRow": 25,
    "widgetName": "inp_moduleDescription",
    "displayName": "Input",
    "searchTags": [
        "form",
        "text input",
        "number",
        "textarea"
    ],
    "bottomRow": 36,
    "parentRowSpace": 10,
    "autoFocus": false,
    "hideCard": false,
    "mobileRightColumn": 21,
    "parentColumnSpace": 10.38037109375,
    "dynamicTriggerPathList": [],
    "labelPosition": "Top",
    "key": "09svys3ytz",
    "labelTextSize": "0.875rem",
    "isDeprecated": false,
    "rightColumn": 63,
    "widgetId": "6xli1wnku2",
    "minWidth": 450,
    "label": "Description",
    "parentId": "fn1suqgpfa",
    "labelAlignment": "left",
    "renderMode": "CANVAS",
    "mobileTopRow": 18,
    "responsiveBehavior": "fill",
    "mobileLeftColumn": 1,
    "maxDynamicHeight": 9000,
    "shouldAllowAutofill": false,
    "iconAlign": "left",
    "defaultText": "{{utils.activeModule ? utils.activeModule.Description : ''}}",
    "minDynamicHeight": 4
}